findimports.py
findimports-3.0.0.dist-info/licenses/LICENSE
findimports-3.0.0.dist-info/METADATA
findimports-3.0.0.dist-info/WHEEL
findimports-3.0.0.dist-info/entry_points.txt
findimports-3.0.0.dist-info/top_level.txt
findimports-3.0.0.dist-info/RECORD
